py2flowchart/__init__.py
py2flowchart/core.py
py2flowchart/if_leap_year.py
py2flowchart/test2.py
py2flowchart-0.0.3.dist-info/LICENSE
py2flowchart-0.0.3.dist-info/METADATA
py2flowchart-0.0.3.dist-info/WHEEL
py2flowchart-0.0.3.dist-info/top_level.txt
py2flowchart-0.0.3.dist-info/RECORD
