Metadata-Version: 2.1
Name: py2flowchart
Version: 0.0.3
Summary: Generates flowchart from Python functions.
Home-page: https://github.com/dstang2000/py2flowchart
Author: Tang Dashi
Author-email: dstang2000@263.net
License: MIT
Keywords: python flow flowchart
Classifier: Framework :: IPython
Classifier: Framework :: Jupyter
Classifier: License :: OSI Approved :: MIT License
Classifier: Programming Language :: Python :: 3.6
Classifier: Programming Language :: Python :: 3.7
Classifier: Programming Language :: Python :: 3.8
Classifier: Programming Language :: Python
Classifier: Topic :: Scientific/Engineering :: Visualization
Classifier: Topic :: Software Development :: Code Generators
Classifier: Topic :: Text Processing :: Markup
Requires-Python: >=3.6
License-File: LICENSE
Requires-Dist: dill>=0.3.2
